bert_classifier/__init__.py
bert_classifier/bert_mt_classifier.py
bert_classifier/data_loader.py
bert_classifier/eval.py
bert_classifier/eval_topk.py
bert_classifier/test.py
bert_gen_once/__init__.py
bert_gen_once/bert_once.py
bert_gen_once/data_loader.py
bert_gen_once/test.py
bert_gen_onebyone/__init__.py
bert_gen_onebyone/bert_onebyone.py
bert_gen_onebyone/data_loader.py
bert_gen_onebyone/test.py
bert_qa/__init__.py
bert_qa/bert_qa.py
bert_qa/data_loader.py
bert_qa/eval.py
bert_qa/test.py
bert_tagging/__init__.py
bert_tagging/bert_tagging.py
bert_tagging/data_loader.py
bert_tagging/eval.py
bert_tagging/test.py
unibert/__init__.py
unibert/train.py
unibert/bert_classifier/__init__.py
unibert/bert_classifier/bert_mt_classifier.py
unibert/bert_classifier/data_loader.py
unibert/bert_classifier/eval.py
unibert/bert_classifier/eval_topk.py
unibert/bert_classifier/test.py
unibert/bert_gen_once/__init__.py
unibert/bert_gen_once/bert_once.py
unibert/bert_gen_once/data_loader.py
unibert/bert_gen_once/test.py
unibert/bert_gen_onebyone/__init__.py
unibert/bert_gen_onebyone/bert_onebyone.py
unibert/bert_gen_onebyone/data_loader.py
unibert/bert_gen_onebyone/test.py
unibert/bert_qa/__init__.py
unibert/bert_qa/bert_qa.py
unibert/bert_qa/data_loader.py
unibert/bert_qa/eval.py
unibert/bert_qa/test.py
unibert/bert_tagging/__init__.py
unibert/bert_tagging/bert_tagging.py
unibert/bert_tagging/data_loader.py
unibert/bert_tagging/demo.py
unibert/bert_tagging/eval.py
unibert/bert_tagging/test.py
uniBert-0.2.1.dist-info/METADATA
uniBert-0.2.1.dist-info/WHEEL
uniBert-0.2.1.dist-info/top_level.txt
uniBert-0.2.1.dist-info/RECORD
