Metadata-Version: 2.1
Name: uniBert
Version: 0.2.1
Summary: Bert multi-task multi-class multi-label classification & text generation & tagging
Home-page: https://github.com/voidful/uniBert
Author: Voidful
Author-email: voidful.stack@gmail.com
License: UNKNOWN
Keywords: nlp bert multi task class label classification generation
Platform: UNKNOWN
Classifier: Development Status :: 4 - Beta
Classifier: Intended Audience :: Developers
Classifier: Topic :: Software Development :: Build Tools
Classifier: License :: OSI Approved :: MIT License
Classifier: Programming Language :: Python :: 3
Classifier: Programming Language :: Python :: 3.4
Classifier: Programming Language :: Python :: 3.5
Classifier: Programming Language :: Python :: 3.6
